InsuLearner/__init__.py
InsuLearner/carbohydrate_sensitivity_factor.py
InsuLearner/insulearner.py
InsuLearner/tidepool/__init__.py
InsuLearner/tidepool/tidepool_api.py
InsuLearner/tidepool/tidepool_user_model.py
InsuLearner/util.py
InsuLearner/visualize_user_data.py
insulearner-0.1.6.dist-info/LICENSE.txt
insulearner-0.1.6.dist-info/METADATA
insulearner-0.1.6.dist-info/WHEEL
insulearner-0.1.6.dist-info/entry_points.txt
insulearner-0.1.6.dist-info/RECORD
