Metadata-Version: 2.1
Name: insulearner
Version: 0.1.6
Summary: Estimate Insulin Pump Settings using Machine Learning
Home-page: https://www.cameronsummers.com/how_I_calculate_my_sons_insulin_pump_settings_with_machine_learning
License: GPL-3.0-only
Keywords: insulin,diabetes,pump,settings,type 1,carbohydrate ratio,insulin sensitivity factor,basa rate
Author: Cameron Summers
Author-email: contact@cameronsummers.com
Requires-Python: >3.8
Classifier: Intended Audience :: Healthcare Industry
Classifier: Intended Audience :: Science/Research
Classifier: License :: OSI Approved :: GNU General Public License v3 (GPLv3)
Classifier: Programming Language :: Python
Classifier: Programming Language :: Python :: 3
Classifier: Programming Language :: Python :: 3.9
Classifier: Programming Language :: Python :: 3.10
Classifier: Programming Language :: Python :: 3.11
Classifier: Programming Language :: Python :: 3.8
Classifier: Topic :: Scientific/Engineering :: Artificial Intelligence
Classifier: Topic :: Scientific/Engineering :: Mathematics
Classifier: Topic :: Scientific/Engineering :: Medical Science Apps.
Requires-Dist: matplotlib (>=3.7.1,<4.0.0)
Requires-Dist: numpy (>=1.24.2,<2.0.0)
Requires-Dist: pandas (>=2.0.0,<3.0.0)
Requires-Dist: pytest (>=7.2.2,<8.0.0)
Requires-Dist: requests (>=2.28.2,<3.0.0)
Requires-Dist: scikit-learn (>=1.2.2,<2.0.0)
Requires-Dist: scipy (>=1.10.1,<2.0.0)
Requires-Dist: seaborn (>=0.12.2,<0.13.0)
Project-URL: Repository, https://github.com/scaubrey/InsuLearner
